yasimavr/__init__.py
yasimavr/__main__.py
yasimavr/cli/simrun.py
yasimavr/cli/__init__.py
yasimavr/device_library/accessors.py
yasimavr/device_library/arch_AVR.py
yasimavr/device_library/arch_XT.py
yasimavr/device_library/descriptors.py
yasimavr/device_library/__init__.py
yasimavr/device_library/builders/dev_megaxx8.py
yasimavr/device_library/builders/dev_mega_0series.py
yasimavr/device_library/builders/dev_tinyx4.py
yasimavr/device_library/builders/dev_tiny_0series.py
yasimavr/device_library/builders/_base.py
yasimavr/device_library/builders/_builders_arch_avr.py
yasimavr/device_library/builders/_builders_arch_xt.py
yasimavr/device_library/builders/__init__.py
yasimavr/device_library/configs/### device config template ###.yml
yasimavr/device_library/configs/ArchXT_analog.yml
yasimavr/device_library/configs/ArchXT_controllers.yml
yasimavr/device_library/configs/ArchXT_interfaces.yml
yasimavr/device_library/configs/ArchXT_timers.yml
yasimavr/device_library/configs/atmega1608.yml
yasimavr/device_library/configs/atmega1609.yml
yasimavr/device_library/configs/atmega168.yml
yasimavr/device_library/configs/atmega168p.yml
yasimavr/device_library/configs/atmega3208.yml
yasimavr/device_library/configs/atmega3209.yml
yasimavr/device_library/configs/atmega328.yml
yasimavr/device_library/configs/atmega328p.yml
yasimavr/device_library/configs/atmega48.yml
yasimavr/device_library/configs/atmega4808.yml
yasimavr/device_library/configs/atmega4809.yml
yasimavr/device_library/configs/atmega48p.yml
yasimavr/device_library/configs/atmega808.yml
yasimavr/device_library/configs/atmega809.yml
yasimavr/device_library/configs/atmega88.yml
yasimavr/device_library/configs/atmega88p.yml
yasimavr/device_library/configs/attiny1604.yml
yasimavr/device_library/configs/attiny1606.yml
yasimavr/device_library/configs/attiny1607.yml
yasimavr/device_library/configs/attiny202.yml
yasimavr/device_library/configs/attiny204.yml
yasimavr/device_library/configs/attiny24.yml
yasimavr-0.1.5.dist-info/DELVEWHEEL
yasimavr-0.1.5.dist-info/METADATA
yasimavr-0.1.5.dist-info/RECORD
yasimavr-0.1.5.dist-info/top_level.txt
yasimavr-0.1.5.dist-info/WHEEL
yasimavr-0.1.5.dist-info/licenses/LICENSE
