Metadata-Version: 2.4
Name: yasimavr
Version: 0.1.5
Summary: Yet Another SIMulator for AVR
Home-page: https://github.com/clesav/yasimavr
Author: C. Savergne
Author-email: csavergne@yahoo.com
License: GPLv3
Project-URL: Source Code, https://github.com/clesav/yasimavr
Project-URL: Bug Tracker, https://github.com/clesav/yasimavr/issues
Keywords: avr simavr
Platform: Any
Classifier: License :: OSI Approved :: GNU General Public License v3 or later (GPLv3+)
Classifier: Natural Language :: English
Classifier: Operating System :: OS Independent
Classifier: Programming Language :: C++
Classifier: Programming Language :: Python :: 3.7
Classifier: Programming Language :: Python :: 3.8
Classifier: Programming Language :: Python :: 3.9
Classifier: Programming Language :: Python :: 3.10
Classifier: Programming Language :: Python :: 3.11
Classifier: Programming Language :: Python :: 3.12
Classifier: Programming Language :: Python :: 3.13
Classifier: Topic :: Scientific/Engineering
Requires-Python: >=3.7
License-File: LICENSE
Requires-Dist: pyYAML
Requires-Dist: pyvcd
Dynamic: author
Dynamic: author-email
Dynamic: classifier
Dynamic: description
Dynamic: description-content-type
Dynamic: home-page
Dynamic: keywords
Dynamic: license
Dynamic: license-file
Dynamic: platform
Dynamic: project-url
Dynamic: requires-dist
Dynamic: requires-python
Dynamic: summary
